clusterq/__init__.py
clusterq/fileutils.py
clusterq/main.py
clusterq/parsing.py
clusterq/queue.py
clusterq/readmol.py
clusterq/readspec.py
clusterq/scripts.py
clusterq/shared.py
clusterq/submit.py
clusterq/utils.py
clusterq/iospecs/autodock/iospec.json
clusterq/iospecs/demon/iospec.json
clusterq/iospecs/dftbplus/iospec.json
clusterq/iospecs/gaussian/iospec.json
clusterq/iospecs/orca/iospec.json
clusterq/iospecs/vasp/iospec.json
clusterq/schedulers/lava/config.json
clusterq/schedulers/lsf/config.json
clusterq/schedulers/slurm/config.json
clusterq/schedulers/torque/config.json
clusterq-0.1.8.post2.data/scripts/jobsync
clusterq-0.1.8.post2.dist-info/LICENSE
clusterq-0.1.8.post2.dist-info/METADATA
clusterq-0.1.8.post2.dist-info/WHEEL
clusterq-0.1.8.post2.dist-info/entry_points.txt
clusterq-0.1.8.post2.dist-info/top_level.txt
clusterq-0.1.8.post2.dist-info/RECORD
